case_conversion/__init__.py
case_conversion/acronym.py
case_conversion/alias.py
case_conversion/converter.py
case_conversion/parser.py
case_conversion/unicode_char.py
case_conversion-3.0.2.dist-info/METADATA
case_conversion-3.0.2.dist-info/WHEEL
case_conversion-3.0.2.dist-info/licenses/LICENSE.md
case_conversion-3.0.2.dist-info/RECORD
