Metadata-Version: 2.4
Name: case-conversion
Version: 3.0.2
Summary: Convert between different types of cases (unicode supported)
Project-URL: Issues, https://github.com/AlejandroFrias/case-conversion/issues
Project-URL: Source, https://github.com/AlejandroFrias/case-conversion
Author-email: Alejandro Frias <joker454@gmail.com>
Maintainer-email: Alejandro Frias <joker454@gmail.com>
License-Expression: MIT
License-File: LICENSE.md
Keywords: camel,case,conversion,convert,kebab,pascal,snake,spinal,unicode
Classifier: Development Status :: 5 - Production/Stable
Classifier: Intended Audience :: Developers
Classifier: Programming Language :: Python :: 3
Classifier: Programming Language :: Python :: 3 :: Only
Classifier: Programming Language :: Python :: 3.10
Classifier: Programming Language :: Python :: 3.11
Classifier: Programming Language :: Python :: 3.12
Classifier: Programming Language :: Python :: 3.13
Requires-Python: >=3.10
